DeviceUAgen/DeviceUAgen.py
DeviceUAgen/__init__.py
deviceuagen-0.1.1.dist-info/METADATA
deviceuagen-0.1.1.dist-info/WHEEL
deviceuagen-0.1.1.dist-info/top_level.txt
deviceuagen-0.1.1.dist-info/RECORD
