Metadata-Version: 2.4
Name: DeviceUAgen
Version: 0.1.1
Summary: Generator User-Agent untuk berbagai perangkat
Home-page: https://github.com/Fajarrrrky/DeviceUAgen
Author: Fajarrrrky
Author-email: saepulfajar440@gmail.com
Classifier: Programming Language :: Python :: 3
Classifier: License :: OSI Approved :: MIT License
Classifier: Operating System :: OS Independent
Requires-Python: >=3.6
Dynamic: author
Dynamic: author-email
Dynamic: classifier
Dynamic: description
Dynamic: description-content-type
Dynamic: home-page
Dynamic: requires-python
Dynamic: summary
